cmind/__init__.py
cmind/__main__.py
cmind/artifact.py
cmind/automation.py
cmind/cli.py
cmind/config.py
cmind/core.py
cmind/index.py
cmind/net.py
cmind/repo.py
cmind/repos.py
cmind/utils.py
cmind/repo/README.md
cmind/repo/cmr.yaml
cmind/repo/automation/automation/README.md
cmind/repo/automation/automation/_cm.json
cmind/repo/automation/automation/module.py
cmind/repo/automation/automation/module_dummy.py
cmind/repo/automation/automation/module_misc.py
cmind/repo/automation/automation/modulex_dummy.py
cmind/repo/automation/automation/template_list_of_automations.md
cmind/repo/automation/ckx/README.md
cmind/repo/automation/ckx/_cm.json
cmind/repo/automation/ckx/module.py
cmind/repo/automation/core/README.md
cmind/repo/automation/core/_cm.json
cmind/repo/automation/core/module.py
cmind/repo/automation/core/module_misc.py
cmind/repo/automation/core/cm_60cb625a46b38610/__init__.py
cmind/repo/automation/core/cm_60cb625a46b38610/misc.py
cmind/repo/automation/mlc/_cm.json
cmind/repo/automation/mlc/module.py
cmind/repo/automation/mlcr/_cm.json
cmind/repo/automation/mlcr/module.py
cmind/repo/automation/repo/README-extra.md
cmind/repo/automation/repo/README.md
cmind/repo/automation/repo/_cm.json
cmind/repo/automation/repo/module.py
cmind-4.2.0.dist-info/licenses/LICENSE.md
cmind-4.2.0.dist-info/METADATA
cmind-4.2.0.dist-info/WHEEL
cmind-4.2.0.dist-info/entry_points.txt
cmind-4.2.0.dist-info/top_level.txt
cmind-4.2.0.dist-info/RECORD
