Metadata-Version: 2.4
Name: cmind
Version: 4.2.0
Summary: Common Metadata eXchange framework (CMX) and Collective Mind automation framework (CM)
Author-email: Grigori Fursin <grigori.fursin@ctuning.org>
Maintainer-email: Grigori Fursin <grigori.fursin@ctuning.org>
License: Apache 2.0
Project-URL: Homepage, https://cKnowledge.org
Project-URL: Documentation, https://docs.mlcommons.org/ck
Project-URL: Repository, https://github.com/mlcommons/ck/tree/master/cm
Project-URL: Issues, https://github.com/mlcommons/ck/issues
Project-URL: Changelog, https://github.com/mlcommons/ck/blob/master/cm/CHANGES.md
Keywords: cmind,cm,cmx,cmx-mlcflow,cmx-mlcr,common metadata exchange,collective mind,automation,portability,reusability,mlops,devops,vmlops,api,cli
Classifier: License :: OSI Approved :: Apache Software License
Classifier: Operating System :: OS Independent
Classifier: Programming Language :: Python :: 3.8
Classifier: Programming Language :: Python :: 3.9
Classifier: Programming Language :: Python :: 3.10
Classifier: Programming Language :: Python :: 3.11
Classifier: Programming Language :: Python :: 3.12
Requires-Python: >=3.7
License-File: LICENSE.md
Requires-Dist: pyyaml
Requires-Dist: requests
Requires-Dist: setuptools
Requires-Dist: wheel
Requires-Dist: giturlparse
Requires-Dist: tabulate
Dynamic: license-file
